{
  "updated_at": "2026-04-09T04:53:21Z",
  "repos": {
    "LANimals": {
      "stars": 5,
      "forks": 1,
      "open_issues": 0,
      "pushed_at": "2026-04-05T21:19:00Z",
      "status": "warning"
    },
    "drift_orchestrator": {
      "stars": 0,
      "forks": 0,
      "open_issues": 0,
      "pushed_at": "2026-04-07T16:43:28Z",
      "status": "warning"
    },
    "OpenSight": {
      "stars": 0,
      "forks": 0,
      "open_issues": 0,
      "pushed_at": "2026-03-25T23:03:39Z",
      "status": "idle"
    },
    "SHENRON": {
      "stars": 0,
      "forks": 0,
      "open_issues": 0,
      "pushed_at": null,
      "status": "idle"
    },
    "LANIMORPH": {
      "stars": 0,
      "forks": 0,
      "open_issues": 0,
      "pushed_at": "2026-04-04T20:59:27Z",
      "status": "warning"
    },
    "PHANTOM": {
      "stars": 0,
      "forks": 0,
      "open_issues": 0,
      "pushed_at": "2026-04-05T21:03:23Z",
      "status": "warning"
    },
    "chain": {
      "stars": 0,
      "forks": 0,
      "open_issues": 0,
      "pushed_at": "2026-03-27T01:03:31Z",
      "status": "idle"
    },
    "aliasOS": {
      "stars": 0,
      "forks": 0,
      "open_issues": 0,
      "pushed_at": "2026-04-04T22:53:52Z",
      "status": "warning"
    },
    "LUNE": {
      "stars": 6,
      "forks": 0,
      "open_issues": 0,
      "pushed_at": "2026-04-05T21:09:01Z",
      "status": "warning"
    },
    "zer0DAYSlater": {
      "stars": 3,
      "forks": 2,
      "open_issues": 0,
      "pushed_at": "2026-04-05T21:06:18Z",
      "status": "warning"
    },
    "HYDRA": {
      "stars": 0,
      "forks": 0,
      "open_issues": 0,
      "pushed_at": null,
      "status": "idle"
    },
    "Pickle Hunter": {
      "stars": 0,
      "forks": 0,
      "open_issues": 0,
      "pushed_at": null,
      "status": "idle"
    },
    "bad_BANANA": {
      "stars": 3,
      "forks": 0,
      "open_issues": 0,
      "pushed_at": "2026-03-25T21:11:41Z",
      "status": "idle"
    },
    "DevToReconSuite": {
      "stars": 0,
      "forks": 0,
      "open_issues": 0,
      "pushed_at": null,
      "status": "idle"
    },
    "repo_alias_forge": {
      "stars": 0,
      "forks": 0,
      "open_issues": 0,
      "pushed_at": null,
      "status": "idle"
    },
    "OWN": {
      "stars": 1,
      "forks": 0,
      "open_issues": 0,
      "pushed_at": "2026-04-05T21:21:10Z",
      "status": "warning"
    },
    "Blackglass": {
      "stars": 0,
      "forks": 0,
      "open_issues": 0,
      "pushed_at": null,
      "status": "idle"
    },
    "pwn": {
      "stars": 1,
      "forks": 0,
      "open_issues": 0,
      "pushed_at": "2026-03-25T21:10:39Z",
      "status": "idle"
    }
  }
}
